lyricore-0.1.3.dist-info/METADATA
lyricore-0.1.3.dist-info/WHEEL
lyricore/__init__.py
lyricore/_lyricore.cpython-312-darwin.so
lyricore/_lyricore_py.pyi
lyricore/_queue.py
lyricore/actor_wrapper.py
lyricore/autoscaler/__init__.py
lyricore/autoscaler/cluster_manager.py
lyricore/autoscaler/distributed_actor_system.py
lyricore/error.py
lyricore/eventbus.py
lyricore/object_store.py
lyricore/pickle.py
lyricore/proxy_ref.py
lyricore/py_actor.py
lyricore/router.py
lyricore/serialization.py
lyricore/utils.py
lyricore-0.1.3.dist-info/RECORD
