Metadata-Version: 2.4
Name: lyricore
Version: 0.1.3
Classifier: Development Status :: 3 - Alpha
Classifier: Programming Language :: Python
Classifier: Programming Language :: Python :: 3
Classifier: Programming Language :: Python :: 3 :: Only
Classifier: Programming Language :: Python :: 3.10
Classifier: Programming Language :: Python :: 3.11
Classifier: Programming Language :: Python :: 3.12
Classifier: Programming Language :: Python :: 3.13
Classifier: Programming Language :: Python :: 3.14
Classifier: Programming Language :: Rust
Classifier: Intended Audience :: Developers
Classifier: Intended Audience :: Information Technology
Classifier: Operating System :: POSIX :: Linux
Classifier: Operating System :: Microsoft :: Windows
Classifier: Operating System :: MacOS
Classifier: Typing :: Typed
Requires-Dist: cloudpickle>=3.1.1
Requires-Dist: pympler>=1.1
Requires-Dist: typing-extensions>=4.0.0 ; python_full_version < '3.10'
Summary: 
Home-Page: https://github.com/fangyinc/lyric
License-Expression: MIT
Requires-Python: >=3.9
Project-URL: Homepage, https://github.com/lyric-project/lyricore
Project-URL: Funding, https://github.com/lyric-project
Project-URL: Source, https://github.com/lyric-project/lyricore
